{
  "bot-name": "ALM-XD",
  "description": "ᴊᴀᴠᴀsᴄʀɪᴘᴛ ᴡʜᴀᴛsᴀᴘᴘ ʙᴏᴛ ᴄʀᴇᴀᴛᴇᴅ ʙʏ ᴍᴀʟᴠɪɴ ᴋɪɴɢ",
  "logo": "https://files.catbox.moe/juxfce.jpg",
  "keywords": ["bot"],
  "documentation-link": "https://new-session-2ag9.onrender.com/",
    "owner-verification":"malvink003@gmail.com",
  
  "env": {
    "SESSION_ID": {
      "description": "Must Start with 'malvin~'",
      "required": true,
      "value": ""
    },
      "BOT_NAME": {
        "description": "ALM-MD",
        "required": true,
        "value": "public"      
    },  
    "MODE": {
      "description": "Set private/public/inbox/groups",
      "required": false,
      "value": "public"
     },
   
    "PREFIX": {
      "description": "Your Bot Prefix (default: .) You can put your own custom prefix",
      "required": true,
      "value": "."
    },
    
    "OWNER_NAME": {
      "description": "Almach",
      "required": true,
      "value": "public"
    },
    "OWNER_NUMBER": {
      "description": "255683174517",
      "required": true,
      "value": "public"
    },
    
    "PRESENCE": {
      "description": "Put online/typing/recording/unavailable",
      "required": true,
      "value": "online"

    }
  }
}
